deadline/keyshot_adaptor/__init__.py
deadline/keyshot_adaptor/_version.py
deadline/keyshot_adaptor/KeyShotAdaptor/KeyShotAdaptor.json
deadline/keyshot_adaptor/KeyShotAdaptor/__init__.py
deadline/keyshot_adaptor/KeyShotAdaptor/__main__.py
deadline/keyshot_adaptor/KeyShotAdaptor/adaptor.py
deadline/keyshot_adaptor/KeyShotAdaptor/schemas/init_data.schema.json
deadline/keyshot_adaptor/KeyShotAdaptor/schemas/run_data.schema.json
deadline/keyshot_adaptor/KeyShotClient/__init__.py
deadline/keyshot_adaptor/KeyShotClient/keyshot_client.py
deadline/keyshot_adaptor/KeyShotClient/keyshot_handler.py
deadline/keyshot_submitter/Submit to AWS Deadline Cloud.py
deadline/keyshot_submitter/__init__.py
deadline/keyshot_submitter/_version.py
deadline_cloud_for_keyshot-0.4.3.dist-info/METADATA
deadline_cloud_for_keyshot-0.4.3.dist-info/WHEEL
deadline_cloud_for_keyshot-0.4.3.dist-info/entry_points.txt
deadline_cloud_for_keyshot-0.4.3.dist-info/licenses/LICENSE
deadline_cloud_for_keyshot-0.4.3.dist-info/licenses/NOTICE
deadline_cloud_for_keyshot-0.4.3.dist-info/RECORD
